mumle/__init__.py
mumle/api/__init__.py
mumle/api/cd.py
mumle/api/od.py
mumle/bootstrap/__init__.py
mumle/bootstrap/pn.py
mumle/bootstrap/primitive.py
mumle/bootstrap/scd.py
mumle/concrete_syntax/__init__.py
mumle/concrete_syntax/common.py
mumle/concrete_syntax/graphviz/__init__.py
mumle/concrete_syntax/graphviz/make_url.py
mumle/concrete_syntax/graphviz/renderer.py
mumle/concrete_syntax/plantuml/__init__.py
mumle/concrete_syntax/plantuml/make_url.py
mumle/concrete_syntax/plantuml/renderer.py
mumle/concrete_syntax/textual_cd/__init__.py
mumle/concrete_syntax/textual_cd/parser.py
mumle/concrete_syntax/textual_od/__init__.py
mumle/concrete_syntax/textual_od/objectdiagrams.jinja2
mumle/concrete_syntax/textual_od/parser.py
mumle/concrete_syntax/textual_od/readme.txt
mumle/concrete_syntax/textual_od/renderer.py
mumle/concrete_syntax/textual_od/renderer_jinja2.py
mumle/framework/__init__.py
mumle/framework/conformance.py
mumle/framework/interactive_prompt.py
mumle/framework/manager.py
mumle/framework/prompt_questions.py
mumle/services/__init__.py
mumle/services/bottom/V0.py
mumle/services/bottom/V1.py
mumle/services/bottom/__init__.py
mumle/services/od.py
mumle/services/pn.py
mumle/services/point/__init__.py
mumle/services/point/cartesian.py
mumle/services/point/polar.py
mumle/services/primitives/__init__.py
mumle/services/primitives/actioncode_type.py
mumle/services/primitives/boolean_type.py
mumle/services/primitives/bytes_type.py
mumle/services/primitives/float_type.py
mumle/services/primitives/integer_type.py
mumle/services/primitives/string_type.py
mumle/services/primitives/type_type.py
mumle/services/scd.py
mumle/state/__init__.py
mumle/state/base.py
mumle/state/devstate.py
mumle/state/neo4jstate.py
mumle/state/pystate.py
mumle/state/rdfstate.py
mumle/transformation/__init__.py
mumle/transformation/cloner.py
mumle/transformation/matcher.py
mumle/transformation/merger.py
mumle/transformation/ramify.py
mumle/transformation/rewriter.py
mumle/transformation/rule.py
mumle-0.0.3.dist-info/WHEEL
mumle-0.0.3.dist-info/entry_points.txt
mumle-0.0.3.dist-info/METADATA
mumle-0.0.3.dist-info/RECORD
