Metadata-Version: 2.3
Name: mumle
Version: 0.0.3
Summary: Tiny (meta-)modeling framework.
Keywords: modeling
Author: Arkadiusz Michał Ryś, Joeri Exelmans, Andrei Bondarenko, Robbe Teughels, Inte Vleminckx
Author-email: Arkadiusz Michał Ryś <Arkadiusz.Michal.Rys@gmail.com>, Joeri Exelmans <joeri.exelmans@gmail.com>, Andrei Bondarenko <andrei.i.bondarenko@gmail.com>, Robbe Teughels <robbe.teughels@student.uantwerpen.be>, Inte Vleminckx <inte.vleminckx@student.uantwerpen.be>
License: MIT License
Classifier: License :: OSI Approved :: MIT License
Classifier: Programming Language :: Python :: 3
Classifier: Development Status :: 2 - Pre-Alpha
Classifier: Intended Audience :: Developers
Classifier: Natural Language :: English
Requires-Dist: lark>=1.1.9,<2
Requires-Dist: jinja2>=3.1.4,<4
Requires-Dist: rdflib>=7.1.4,<8
Requires-Dist: neo4j>=5.28.1,<6
Requires-Dist: ruff ; extra == 'dev'
Requires-Dist: invoke ; extra == 'dev'
Requires-Dist: vermin ; extra == 'dev'
Requires-Dist: sphinx ; extra == 'doc'
Requires-Dist: sphinx-rtd-theme ; extra == 'doc'
Requires-Dist: pytest ; extra == 'test'
Requires-Python: >=3.12
Project-URL: source, https://git.rys.one/phd/mumle
Provides-Extra: dev
Provides-Extra: doc
Provides-Extra: test
